interpol/__init__.py
interpol/_core.py
interpol/_version.py
interpol/tests/__init__.py
interpol/tests/test_interpol.py
interpol-0.1.0.dist-info/AUTHORS.rst
interpol-0.1.0.dist-info/LICENSE
interpol-0.1.0.dist-info/METADATA
interpol-0.1.0.dist-info/WHEEL
interpol-0.1.0.dist-info/entry_points.txt
interpol-0.1.0.dist-info/top_level.txt
interpol-0.1.0.dist-info/RECORD
