Metadata-Version: 2.1
Name: interpol
Version: 0.1.0
Summary: Python package for doing interpolation in the plane.
Home-page: https://github.com/rwijtvliet/interpol
Author: rwijtvliet
Author-email: rwijtvliet@gmail.com
License: BSD (3-clause)
Platform: UNKNOWN
Classifier: Development Status :: 2 - Pre-Alpha
Classifier: Natural Language :: English
Classifier: Programming Language :: Python :: 3
Requires-Python: >=3.7
Requires-Dist: polygonation
Requires-Dist: numpy
